maestria/__init__.py
maestria/cli.py
maestria/config.py
maestria/context.py
maestria/environment.py
maestria/security.py
maestria/commands/__init__.py
maestria/commands/audit.py
maestria/commands/build.py
maestria/commands/env.py
maestria/commands/helpers.py
maestria/commands/init.py
maestria/commands/install.py
maestria/commands/lint.py
maestria/commands/plugin.py
maestria/commands/release.py
maestria/commands/run.py
maestria/commands/test.py
maestria/plugins/__init__.py
maestria/templates/__init__.py
maestria/templates/data/basic/.bumpversion.cfg
maestria/templates/data/basic/MANIFEST.in
maestria/templates/data/basic/README.md
maestria/templates/data/basic/pyproject.toml
maestria/templates/data/basic/setup.py
maestria/templates/data/basic/docs/index.md
maestria/templates/data/basic/docs/installation.md
maestria/templates/data/basic/docs/quickstart.md
maestria/templates/data/basic/docs/api/calculator.md
maestria/templates/data/basic/docs/api/index.md
maestria/templates/data/basic/docs/cli/batch.md
maestria/templates/data/basic/docs/cli/calculate.md
maestria/templates/data/basic/docs/cli/index.md
maestria/templates/data/basic/docs/cli/memory.md
maestria/templates/data/basic/docs/cli/shell.md
maestria/templates/data/basic/docs/development/contributing.md
maestria/templates/data/basic/docs/tutorials/getting-started-cli.md
maestria/templates/data/basic/docs/tutorials/index.md
maestria/templates/data/basic/tests/__init__.py
maestria/templates/data/basic/tests/conftest.py
maestria/templates/data/basic/tests/test_cli.py
maestria/templates/data/basic/tests/api/test_calculator.py
maestria/templates/data/basic/tests/cli/test_batch_commands.py
maestria/templates/data/basic/tests/cli/test_interactive_shell.py
maestria/templates/data/basic/tests/data/sample_numbers.json
maestria/templates/data/basic/{{project_slug}}/__init__.py
maestria/templates/data/basic/{{project_slug}}/cli.py
maestria/templates/data/basic/{{project_slug}}/api/__init__.py
maestria-0.9.1.dist-info/licenses/LICENSE
maestria-0.9.1.dist-info/licenses/NOTICE
maestria-0.9.1.dist-info/METADATA
maestria-0.9.1.dist-info/WHEEL
maestria-0.9.1.dist-info/entry_points.txt
maestria-0.9.1.dist-info/top_level.txt
maestria-0.9.1.dist-info/RECORD
